Metadata-Version: 1.0
Name: GaussBinomial
Version: 1.0
Summary: Gaussian and Binomial distributions
Home-page: UNKNOWN
Author: Oladokun Pelumi
Author-email: UNKNOWN
License: UNKNOWN
Platform: UNKNOWN
